{
  "docusaurus-plugin-content-docs": {
    "default": {
      "path": "/docs",
      "versions": [
        {
          "name": "current",
          "label": "Next",
          "isLast": true,
          "path": "/docs",
          "mainDocId": "Github/LICENSE",
          "docs": [
            {
              "id": "Github/git",
              "path": "/docs/Github/git",
              "sidebar": "tutorialSidebar"
            },
            {
              "id": "Github/git-AI-EDIT",
              "path": "/docs/Github/git-AI-EDIT",
              "sidebar": "tutorialSidebar"
            },
            {
              "id": "Github/gitignore",
              "path": "/docs/Github/gitignore",
              "sidebar": "tutorialSidebar"
            },
            {
              "id": "Github/LICENSE",
              "path": "/docs/Github/LICENSE",
              "sidebar": "tutorialSidebar"
            },
            {
              "id": "MinecraftModding/Intellij/PracticalTips",
              "path": "/docs/MinecraftModding/Intellij/PracticalTips",
              "sidebar": "tutorialSidebar"
            },
            {
              "id": "MinecraftModding/Java/Generics",
              "path": "/docs/MinecraftModding/Java/Generics",
              "sidebar": "tutorialSidebar"
            },
            {
              "id": "MinecraftModding/Java/JavaMemoryModel",
              "path": "/docs/MinecraftModding/Java/JavaMemoryModel",
              "sidebar": "tutorialSidebar"
            },
            {
              "id": "MinecraftModding/Java/static",
              "path": "/docs/MinecraftModding/Java/static",
              "sidebar": "tutorialSidebar"
            },
            {
              "id": "MinecraftModding/Java/Supplier",
              "path": "/docs/MinecraftModding/Java/Supplier",
              "sidebar": "tutorialSidebar"
            },
            {
              "id": "MinecraftModding/MinecraftModding",
              "path": "/docs/MinecraftModding/",
              "sidebar": "tutorialSidebar"
            },
            {
              "id": "Other/keywordexplaining",
              "path": "/docs/Other/keywordexplaining",
              "sidebar": "tutorialSidebar"
            },
            {
              "id": "Other/Neovim",
              "path": "/docs/Other/Neovim",
              "sidebar": "tutorialSidebar"
            },
            {
              "id": "Other/rpgmakerFileStructure",
              "path": "/docs/Other/rpgmakerFileStructure",
              "sidebar": "tutorialSidebar"
            },
            {
              "id": "Other/VSC_hotkey",
              "path": "/docs/Other/VSC_hotkey",
              "sidebar": "tutorialSidebar"
            }
          ],
          "draftIds": [],
          "sidebars": {
            "tutorialSidebar": {
              "link": {
                "path": "/docs/Github/LICENSE",
                "label": "Github/LICENSE"
              }
            }
          }
        }
      ],
      "breadcrumbs": true
    }
  }
}